graph_cordinates/__init__.py
graph_cordinates/graph_cordinates.py
graph_cordinates-0.0.4.dist-info/METADATA
graph_cordinates-0.0.4.dist-info/WHEEL
graph_cordinates-0.0.4.dist-info/top_level.txt
graph_cordinates-0.0.4.dist-info/RECORD
