Metadata-Version: 2.1
Name: graph_cordinates
Version: 0.0.4
Summary: From Image of a curve/graph, extract and store the cordinates pairs in a 2D array 
Author: Ujjawal Kumar (India)
Author-email: <kumarujjawal3621@gmail.com>
Keywords: stock_price,Python,Cordinates,Image,2D Curve
Classifier: Development Status :: 1 - Planning
Classifier: Intended Audience :: Developers
Classifier: Programming Language :: Python :: 3
Classifier: Operating System :: Unix
Classifier: Operating System :: MacOS :: MacOS X
Classifier: Operating System :: Microsoft :: Windows
